v4yve/__init__.py
v4yve/cli.py
v4yve/main.py
v4yve/service.py
v4yve/utils.py
v4yve/app/__init__.py
v4yve/app/main.py
v4yve/app/models.py
v4yve/app/status.py
v4yve/app/__pycache__/__init__.cpython-39.pyc
v4yve/app/__pycache__/status.cpython-39.pyc
v4yve/app/routers/__init__.py
v4yve/app/routers/attack.py
v4yve/app/routers/index.py
v4yve/app/routers/services.py
v4yve/app/static/css/bootstrap.min.css
v4yve/app/static/css/bootstrap.min.css.map
v4yve/app/static/css/index.css
v4yve/app/static/css/intlTelInput.min.css
v4yve/app/static/img/flags.png
v4yve/app/static/img/flags@2x.png
v4yve/app/static/js/index.js
v4yve/app/static/js/intlTelInput.min.js
v4yve/app/static/js/progressbar.min.js
v4yve/app/static/js/progressbar.min.js.map
v4yve/app/templates/index.html
v4yve/services/3040.py
v4yve/services/585gold.py
v4yve/services/585zolotoy.py
v4yve/services/aisttaxi.py
v4yve/services/alfalife.py
v4yve/services/alpari.py
v4yve/services/apteka.py
v4yve/services/service.py
v4yve-0.1.dist-info/METADATA
v4yve-0.1.dist-info/WHEEL
v4yve-0.1.dist-info/entry_points.txt
v4yve-0.1.dist-info/top_level.txt
v4yve-0.1.dist-info/RECORD
