Metadata-Version: 2.1
Name: v4yve
Version: 0.1
Summary: SmSBomb
Home-page: https://vk.com/v4yve
Author: v4vye
Author-email: v4yve@yandex.ru
License: Mozilla Public License 2.0
Platform: UNKNOWN
Classifier: Programming Language :: Python
Classifier: Programming Language :: Python :: 3
Classifier: Programming Language :: Python :: 3.7
Classifier: Operating System :: Android
Classifier: Operating System :: Microsoft :: Windows
Classifier: Topic :: Internet
Classifier: License :: OSI Approved :: Mozilla Public License 2.0 (MPL 2.0)
Requires-Python: >=3.7.0
Requires-Dist: aiofiles
Requires-Dist: click
Requires-Dist: fastapi
Requires-Dist: httpx
Requires-Dist: jinja2
Requires-Dist: loguru
Requires-Dist: phonenumbers
Requires-Dist: pydantic
Requires-Dist: random-user-agent
Requires-Dist: uvicorn
Requires-Dist: wheel
